MANIFEST.in
README.rst
setup.py
pybacor/__init__.py
pybacor.egg-info/PKG-INFO
pybacor.egg-info/SOURCES.txt
pybacor.egg-info/dependency_links.txt
pybacor.egg-info/not-zip-safe
pybacor.egg-info/requires.txt
pybacor.egg-info/top_level.txt
pybacor/api/__init__.py
pybacor/api/config.py
pybacor/api/ktp.py