Metadata-Version: 1.1
Name: pybacor
Version: 1.1.1
Summary: ibacor API for Python
Home-page: http://github.com/yanwarsolah/pybacor
Author: Yanwar Solahudin
Author-email: yanwarsolah@gmail.com
License: MIT
Platform: UNKNOWN
Classifier: Development Status :: 3 - Alpha
Classifier: License :: OSI Approved :: MIT License
Classifier: Programming Language :: Python :: 3
Classifier: Natural Language :: English
Classifier: Intended Audience :: Developers
